groll/__init__.py
groll/__main__.py
groll/diceparser.py
groll/groll.py
groll-0.2.1.dist-info/entry_points.txt
groll-0.2.1.dist-info/LICENSE
groll-0.2.1.dist-info/WHEEL
groll-0.2.1.dist-info/METADATA
groll-0.2.1.dist-info/RECORD
